adage/__init__.py
adage/adageobject.py
adage/backends.py
adage/controllerutils.py
adage/dagstate.py
adage/decorators.py
adage/graph.py
adage/node.py
adage/nodestate.py
adage/pollingexec.py
adage/serialize.py
adage/trackers.py
adage/visualize.py
adage/wflowcontroller.py
adage-0.11.0.dist-info/LICENSE
adage-0.11.0.dist-info/METADATA
adage-0.11.0.dist-info/WHEEL
adage-0.11.0.dist-info/top_level.txt
adage-0.11.0.dist-info/RECORD
