Metadata-Version: 2.1
Name: adage
Version: 0.11.0
Summary: Running dynamic DAG workflows
Home-page: https://github.com/yadage/adage
Author: Lukas Heinrich
Author-email: lukas.heinrich@cern.ch
License: MIT
Project-URL: Documentation, https://github.com/yadage/adage
Project-URL: Source Code, https://github.com/yadage/adage
Project-URL: Issue Tracker, https://github.com/yadage/adage/issues
Keywords: physics yadage
Classifier: Development Status :: 4 - Beta
Classifier: License :: OSI Approved :: MIT License
Classifier: Intended Audience :: Science/Research
Classifier: Topic :: Scientific/Engineering
Classifier: Topic :: Scientific/Engineering :: Physics
Classifier: Programming Language :: Python :: 3
Classifier: Programming Language :: Python :: 3 :: Only
Classifier: Programming Language :: Python :: 3.7
Classifier: Programming Language :: Python :: 3.8
Classifier: Programming Language :: Python :: 3.9
Classifier: Programming Language :: Python :: 3.10
Classifier: Programming Language :: Python :: 3.11
Classifier: Programming Language :: Python :: Implementation :: CPython
Requires-Python: >=3.7
License-File: LICENSE
Requires-Dist: networkx (>=2.4)
Provides-Extra: develop
Requires-Dist: pyflakes ; extra == 'develop'
Requires-Dist: pytest (>=3.2.0) ; extra == 'develop'
Requires-Dist: pytest-cov (>=2.5.1) ; extra == 'develop'
Requires-Dist: python-coveralls ; extra == 'develop'
Provides-Extra: viz
Requires-Dist: pydot (>=1.2.3) ; extra == 'viz'
Requires-Dist: pygraphviz (!=1.8,>=1.0) ; extra == 'viz'
